cronbach/__init__.py
cronbach/cronbach.py
cronbach-0.6.0.dist-info/LICENSE
cronbach-0.6.0.dist-info/WHEEL
cronbach-0.6.0.dist-info/METADATA
cronbach-0.6.0.dist-info/RECORD
