Metadata-Version: 2.1
Name: cronbach
Version: 0.6.0
Summary: Compute Cronbach's alpha statistic
Home-page: https://github.com/datagazing/cronbach
Author: Brendan Strejcek
Author-email: brendan@datagazing.com
Requires-Python: >=3.7
Classifier: License :: OSI Approved :: MIT License
Requires-Dist: numpy
Requires-Dist: pandas
Requires-Dist: scipy
